indralib/__init__.py
indralib/indra_client.py
indralib/indra_downloader.py
indralib/indra_event.py
indralib/indra_module.py
indralib/indra_time.py
indralib/py.typed
indralib/server_config.py
indralib-0.4.4.dist-info/METADATA
indralib-0.4.4.dist-info/WHEEL
indralib-0.4.4.dist-info/top_level.txt
indralib-0.4.4.dist-info/RECORD
