Metadata-Version: 2.4
Name: indralib
Version: 0.4.4
Summary: Client for the Indrajala system
Author-email: Dominik Schlösser <dominik.schloesser@gmail.com>
License-Expression: MIT
Project-URL: Homepage, https://codeberg.org/domschl/indrajala
Project-URL: Bug Tracker, https://codeberg.org/domschl/indrajala/issues
Classifier: Programming Language :: Python :: 3
Classifier: Operating System :: OS Independent
Classifier: Development Status :: 3 - Alpha
Classifier: Typing :: Typed
Requires-Python: >=3.10
Requires-Dist: websockets>=12.0
